sid_signing_tool/__init__.py
sid_signing_tool/__main__.py
sid_signing_tool/api.py
sid_signing_tool/cert.py
sid_signing_tool/certstore/__init__.py
sid_signing_tool/certstore/hsm.py
sid_signing_tool/certstore/mem.py
sid_signing_tool/cli.py
sid_signing_tool/crypto.py
sid_signing_tool/exceptions.py
sid_signing_tool/types.py
sid_signing_tool/util.py
sid_signing_tool-1.2.0.dist-info/LICENSE
sid_signing_tool-1.2.0.dist-info/METADATA
sid_signing_tool-1.2.0.dist-info/NOTICE
sid_signing_tool-1.2.0.dist-info/WHEEL
sid_signing_tool-1.2.0.dist-info/entry_points.txt
sid_signing_tool-1.2.0.dist-info/RECORD
