Metadata-Version: 2.1
Name: sid-signing-tool
Version: 1.2.0
Summary: Tool that generates Sidewalk Certificate Chain with HSM
Author: Sidewalk Team
Author-email: sidewalk-provisioning@amazon.com
Requires-Python: >=3.8,<4.0
Classifier: Programming Language :: Python :: 3
Classifier: Programming Language :: Python :: 3.8
Classifier: Programming Language :: Python :: 3.9
Classifier: Programming Language :: Python :: 3.10
Classifier: Programming Language :: Python :: 3.11
Classifier: Programming Language :: Python :: 3.12
Requires-Dist: cryptography (>=42.0.2,<43.0.0)
Requires-Dist: packaging (>=24.0,<25.0)
Requires-Dist: requests (>=2.31.0,<3.0.0)
Requires-Dist: yubihsm (>=3.0.0,<4.0.0)
